LICENSE
MANIFEST.in
README.md
requirements.txt
setup.py
pytest_log_filter/__init__.py
pytest_log_filter/plugin.py
pytest_log_filter.egg-info/PKG-INFO
pytest_log_filter.egg-info/SOURCES.txt
pytest_log_filter.egg-info/dependency_links.txt
pytest_log_filter.egg-info/entry_points.txt
pytest_log_filter.egg-info/requires.txt
pytest_log_filter.egg-info/top_level.txt
pytest_log_filter.egg-info/zip-safe