Metadata-Version: 2.4
Name: pytest-log-filter
Version: 0.0.2
Summary: Ignore some loggers' log for pytest
Home-page: https://github.com/hanzhichao/pytest-log-filter
Author: Han Zhichao
Author-email: superhin@126.com
License: MIT license
Keywords: pytest,py.test,pytest ignore logs,pytest log filter
Classifier: Framework :: Pytest
Classifier: Programming Language :: Python
Classifier: Topic :: Software Development :: Testing
Classifier: Programming Language :: Python :: 3.7
License-File: LICENSE
Requires-Dist: pytest
Requires-Dist: pytest-runner
Dynamic: author
Dynamic: author-email
Dynamic: classifier
Dynamic: description
Dynamic: description-content-type
Dynamic: home-page
Dynamic: keywords
Dynamic: license
Dynamic: license-file
Dynamic: requires-dist
Dynamic: summary
